<annotation>
	<folder>images</folder>
	<filename>frame45.jpg</filename>
	<path>C:\Users\eric\Desktop\projects\runescape\images\frame45.jpg</path>
	<source>
		<database>Unknown</database>
	</source>
	<size>
		<width>1920</width>
		<height>1080</height>
		<depth>3</depth>
	</size>
	<segmented>0</segmented>
	<object>
		<name>cow</name>
		<pose>Unspecified</pose>
		<truncated>0</truncated>
		<difficult>0</difficult>
		<bndbox>
			<xmin>974</xmin>
			<ymin>22</ymin>
			<xmax>1086</xmax>
			<ymax>122</ymax>
		</bndbox>
	</object>
	<object>
		<name>calf</name>
		<pose>Unspecified</pose>
		<truncated>0</truncated>
		<difficult>0</difficult>
		<bndbox>
			<xmin>1238</xmin>
			<ymin>22</ymin>
			<xmax>1269</xmax>
			<ymax>78</ymax>
		</bndbox>
	</object>
	<object>
		<name>calf</name>
		<pose>Unspecified</pose>
		<truncated>0</truncated>
		<difficult>0</difficult>
		<bndbox>
			<xmin>1354</xmin>
			<ymin>307</ymin>
			<xmax>1394</xmax>
			<ymax>365</ymax>
		</bndbox>
	</object>
	<object>
		<name>calf</name>
		<pose>Unspecified</pose>
		<truncated>0</truncated>
		<difficult>0</difficult>
		<bndbox>
			<xmin>1376</xmin>
			<ymin>582</ymin>
			<xmax>1418</xmax>
			<ymax>648</ymax>
		</bndbox>
	</object>
	<object>
		<name>calf</name>
		<pose>Unspecified</pose>
		<truncated>0</truncated>
		<difficult>0</difficult>
		<bndbox>
			<xmin>974</xmin>
			<ymin>265</ymin>
			<xmax>1002</xmax>
			<ymax>319</ymax>
		</bndbox>
	</object>
	<object>
		<name>cow_drop</name>
		<pose>Unspecified</pose>
		<truncated>0</truncated>
		<difficult>0</difficult>
		<bndbox>
			<xmin>739</xmin>
			<ymin>569</ymin>
			<xmax>775</xmax>
			<ymax>594</ymax>
		</bndbox>
	</object>
	<object>
		<name>cow_drop</name>
		<pose>Unspecified</pose>
		<truncated>0</truncated>
		<difficult>0</difficult>
		<bndbox>
			<xmin>953</xmin>
			<ymin>384</ymin>
			<xmax>980</xmax>
			<ymax>416</ymax>
		</bndbox>
	</object>
	<object>
		<name>cow_drop</name>
		<pose>Unspecified</pose>
		<truncated>0</truncated>
		<difficult>0</difficult>
		<bndbox>
			<xmin>1134</xmin>
			<ymin>305</ymin>
			<xmax>1166</xmax>
			<ymax>327</ymax>
		</bndbox>
	</object>
	<object>
		<name>cow_drop</name>
		<pose>Unspecified</pose>
		<truncated>0</truncated>
		<difficult>0</difficult>
		<bndbox>
			<xmin>1318</xmin>
			<ymin>216</ymin>
			<xmax>1342</xmax>
			<ymax>245</ymax>
		</bndbox>
	</object>
</annotation>
